{
  "db_name": "SQLite",
  "query": "\n        SELECT\n            id,\n            name,\n            source as device_type,\n            created_at\n        FROM elt_source_connections\n        WHERE pairing_status = 'pending'\n        ORDER BY created_at DESC\n        ",
  "describe": {
    "columns": [
      {
        "name": "id",
        "ordinal": 0,
        "type_info": "Text"
      },
      {
        "name": "name",
        "ordinal": 1,
        "type_info": "Text"
      },
      {
        "name": "device_type",
        "ordinal": 2,
        "type_info": "Text"
      },
      {
        "name": "created_at",
        "ordinal": 3,
        "type_info": "Text"
      }
    ],
    "parameters": {
      "Right": 0
    },
    "nullable": [
      true,
      false,
      false,
      false
    ]
  },
  "hash": "371aa5652407a843cabe7026754971c6d4303309f118622ba9fd1b3b47967227"
}
