{
  "db_name": "PostgreSQL",
  "query": "\n        SELECT\n            model_id,\n            display_name,\n            provider,\n            enabled,\n            sort_order,\n            context_window,\n            max_output_tokens,\n            supports_tools,\n            is_default\n        FROM app.models\n        WHERE user_id IS NULL AND enabled = true\n        ORDER BY sort_order ASC\n        ",
  "describe": {
    "columns": [
      {
        "ordinal": 0,
        "name": "model_id",
        "type_info": "Text"
      },
      {
        "ordinal": 1,
        "name": "display_name",
        "type_info": "Text"
      },
      {
        "ordinal": 2,
        "name": "provider",
        "type_info": "Text"
      },
      {
        "ordinal": 3,
        "name": "enabled",
        "type_info": "Bool"
      },
      {
        "ordinal": 4,
        "name": "sort_order",
        "type_info": "Int4"
      },
      {
        "ordinal": 5,
        "name": "context_window",
        "type_info": "Int4"
      },
      {
        "ordinal": 6,
        "name": "max_output_tokens",
        "type_info": "Int4"
      },
      {
        "ordinal": 7,
        "name": "supports_tools",
        "type_info": "Bool"
      },
      {
        "ordinal": 8,
        "name": "is_default",
        "type_info": "Bool"
      }
    ],
    "parameters": {
      "Left": []
    },
    "nullable": [
      false,
      false,
      false,
      false,
      false,
      true,
      true,
      true,
      true
    ]
  },
  "hash": "a6d4e4ca7da6ddecff8d8e9757e11ff8a3fb34779987939ff7032b7af898a498"
}
